upkit/__init__.py
upkit/package_linker.py
upkit/tools.py
upkit/utils.py
upkit/win32.py
upkit/data/create-package/git-ignore.j2
upkit/data/create-package/linkspec.yaml.j2
upkit/data/create-package/package.nuspec.j2
upkit/data/create-package/upkit.yaml.j2
upkit/tests/__init__.py
upkit/tests/test_package_linker.py
upkit-0.4.2.dist-info/LICENSE
upkit-0.4.2.dist-info/METADATA
upkit-0.4.2.dist-info/WHEEL
upkit-0.4.2.dist-info/entry_points.txt
upkit-0.4.2.dist-info/top_level.txt
upkit-0.4.2.dist-info/RECORD
