Metadata-Version: 2.1
Name: upkit
Version: 0.4.2
Summary: Project and package manager for Unity3D
Home-page: https://github.com/finderseyes/upkit
Author: Vu Le (findereyes)
Author-email: tuongvu@gmail.com
License: UNKNOWN
Platform: UNKNOWN
Classifier: Programming Language :: Python :: 2
Classifier: License :: OSI Approved :: MIT License
Classifier: Operating System :: OS Independent
Requires-Dist: xmltodict
Requires-Dist: pyyaml
Requires-Dist: yamlordereddictloader
Requires-Dist: jinja2
Requires-Dist: gitpython
